prompt_contracts-0.4.0.dist-info/licenses/LICENSE
promptcontracts/__init__.py
promptcontracts/cli.py
promptcontracts/core/__init__.py
promptcontracts/core/capability.py
promptcontracts/core/composition.py
promptcontracts/core/loader.py
promptcontracts/core/metrics.py
promptcontracts/core/parser.py
promptcontracts/core/runner.py
promptcontracts/core/sampling.py
promptcontracts/core/validator.py
promptcontracts/core/adapters/__init__.py
promptcontracts/core/adapters/base.py
promptcontracts/core/adapters/embeddings_local.py
promptcontracts/core/adapters/judge_openai.py
promptcontracts/core/adapters/ollama_adapter.py
promptcontracts/core/adapters/openai_adapter.py
promptcontracts/core/checks/__init__.py
promptcontracts/core/checks/enum_value.py
promptcontracts/core/checks/json_required.py
promptcontracts/core/checks/json_valid.py
promptcontracts/core/checks/judge.py
promptcontracts/core/checks/latency_budget.py
promptcontracts/core/checks/regex_absent.py
promptcontracts/core/checks/semantic.py
promptcontracts/core/checks/token_budget.py
promptcontracts/core/reporters/__init__.py
promptcontracts/core/reporters/cli_reporter.py
promptcontracts/core/reporters/json_reporter.py
promptcontracts/core/reporters/junit_reporter.py
promptcontracts/eval/__init__.py
promptcontracts/eval/audit_harness.py
promptcontracts/eval/baselines.py
promptcontracts/eval/bench_loaders.py
promptcontracts/eval/repair_analysis.py
promptcontracts/judge/__init__.py
promptcontracts/judge/protocols.py
promptcontracts/spec/pcsl-v0.1.md
promptcontracts/spec/schema/pcsl-ep.schema.json
promptcontracts/spec/schema/pcsl-es.schema.json
promptcontracts/spec/schema/pcsl-pd.schema.json
promptcontracts/stats/__init__.py
promptcontracts/stats/calibration.py
promptcontracts/stats/intervals.py
promptcontracts/stats/power.py
promptcontracts/stats/preregistration.py
promptcontracts/stats/significance.py
promptcontracts/utils/__init__.py
promptcontracts/utils/errors.py
promptcontracts/utils/hashing.py
promptcontracts/utils/normalization.py
prompt_contracts-0.4.0.dist-info/METADATA
prompt_contracts-0.4.0.dist-info/WHEEL
prompt_contracts-0.4.0.dist-info/entry_points.txt
prompt_contracts-0.4.0.dist-info/top_level.txt
prompt_contracts-0.4.0.dist-info/RECORD
