Metadata-Version: 2.4
Name: prompt-contracts
Version: 0.4.0
Summary: Contract testing framework for LLM prompts - PCSL (Prompt Contract Specification Language)
Author: Philippos Melikidis
Maintainer: Philippos Melikidis
License-Expression: MIT
Project-URL: Homepage, https://github.com/promptcontracts/prompt-contracts
Project-URL: Documentation, https://promptcontracts.org/docs
Project-URL: Repository, https://github.com/promptcontracts/prompt-contracts
Project-URL: Bug Tracker, https://github.com/promptcontracts/prompt-contracts/issues
Keywords: llm,testing,contracts,prompt-engineering,validation,pcsl,openai,ollama,quality-assurance
Classifier: Development Status :: 4 - Beta
Classifier: Intended Audience :: Developers
Classifier: Programming Language :: Python :: 3
Classifier: Programming Language :: Python :: 3.10
Classifier: Programming Language :: Python :: 3.11
Classifier: Programming Language :: Python :: 3.12
Classifier: Programming Language :: Python :: 3.13
Classifier: Topic :: Software Development :: Testing
Classifier: Topic :: Software Development :: Quality Assurance
Classifier: Topic :: Scientific/Engineering :: Artificial Intelligence
Classifier: Typing :: Typed
Requires-Python: >=3.10
License-File: LICENSE
Requires-Dist: pyyaml>=6.0.1
Requires-Dist: jsonschema>=4.0.0
Requires-Dist: jsonpath-ng>=1.6.0
Requires-Dist: openai>=1.0.0
Requires-Dist: httpx>=0.24.0
Requires-Dist: rich>=13.0.0
Requires-Dist: numpy>=1.24.0
Requires-Dist: scipy>=1.10.0
Provides-Extra: dev
Requires-Dist: pytest>=7.0.0; extra == "dev"
Requires-Dist: pytest-cov>=4.0.0; extra == "dev"
Requires-Dist: pytest-mock>=3.10.0; extra == "dev"
Requires-Dist: black>=24.0.0; extra == "dev"
Requires-Dist: isort>=5.13.0; extra == "dev"
Requires-Dist: ruff>=0.1.0; extra == "dev"
Requires-Dist: pre-commit>=3.5.0; extra == "dev"
Requires-Dist: build>=1.0.0; extra == "dev"
Requires-Dist: twine>=4.0.0; extra == "dev"
Provides-Extra: all
Requires-Dist: prompt-contracts[dev]; extra == "all"
Dynamic: license-file
